TIC_TAC_TOE_CLI/tic_tac_toe.py
TIC_TAC_TOE_CLI-1.dist-info/LICENSE
TIC_TAC_TOE_CLI-1.dist-info/METADATA
TIC_TAC_TOE_CLI-1.dist-info/WHEEL
TIC_TAC_TOE_CLI-1.dist-info/entry_points.txt
TIC_TAC_TOE_CLI-1.dist-info/top_level.txt
TIC_TAC_TOE_CLI-1.dist-info/RECORD
